pdf_to_img_converter/__init__.py
pdf_to_img_converter/converter.py
pdf_to_img_converter-0.1.0.dist-info/licenses/LICENSE
tests/__init__.py
tests/test_converter.py
pdf_to_img_converter-0.1.0.dist-info/METADATA
pdf_to_img_converter-0.1.0.dist-info/WHEEL
pdf_to_img_converter-0.1.0.dist-info/top_level.txt
pdf_to_img_converter-0.1.0.dist-info/RECORD
