Metadata-Version: 2.4
Name: pdf_to_img_converter
Version: 0.1.0
Summary: Uma biblioteca Python para converter arquivos PDF em imagens.
Home-page: https://github.com/robertolima-dev/pdf_to_img_converter
Author: Roberto Lima
Author-email: Roberto Lima <robertolima.izphera@gmail.com>
License: MIT
Project-URL: Homepage, https://github.com/robertolima-dev/pdf_to_img_converter
Project-URL: Repository, https://github.com/robertolima-dev/pdf_to_img_converter
Project-URL: Issues, https://github.com/robertolima-dev/pdf_to_img_converter/issues
Requires-Python: >=3.6
License-File: LICENSE
Requires-Dist: pdf2image
Requires-Dist: requests
Requires-Dist: Pillow
Dynamic: author
Dynamic: home-page
Dynamic: license-file
Dynamic: requires-python
